methcomp/__init__.py
methcomp/blandaltman.py
methcomp/glucose.py
methcomp/regression.py
methcomp-1.0.0.dist-info/DESCRIPTION.rst
methcomp-1.0.0.dist-info/METADATA
methcomp-1.0.0.dist-info/RECORD
methcomp-1.0.0.dist-info/WHEEL
methcomp-1.0.0.dist-info/metadata.json
methcomp-1.0.0.dist-info/top_level.txt
