Metadata-Version: 2.0
Name: methcomp
Version: 1.0.0
Summary: methcomp: method comparison for clinical chemistry
Home-page: https://github.com/wptmdoorn/methcomp
Author: William P.T.M. van Doorn
Author-email: wptmdoorn@gmail.com
Maintainer: William P.T.M. van Doorn
Maintainer-email: wptmdoorn@gmail.com
License: MIT
Download-URL: https://github.com/wptmdoorn/methcomp/archive/v1.0.0.tar.gz
Platform: UNKNOWN
Classifier: Programming Language :: Python
Classifier: Programming Language :: Python :: 3.6
Classifier: Programming Language :: Python :: 3.7
Classifier: Intended Audience :: Science/Research
Classifier: License :: OSI Approved :: MIT License
Classifier: Operating System :: OS Independent
Classifier: Topic :: Scientific/Engineering :: Bio-Informatics
Classifier: Topic :: Scientific/Engineering :: Visualization
Requires-Dist: numpy (>=1.17.2)
Requires-Dist: scipy (>=1.3.1)
Requires-Dist: matplotlib (>=3.1.2)
Requires-Dist: pandas
Requires-Dist: shapely
Requires-Dist: statsmodels
